Metadata-Version: 2.1
Name: aad_fastapi_dl37
Version: 1.0.3
Summary: aad_fastapi middleware backend helper for bearer verification with FastAPI and Azure AD
Project-URL: Homepage, https://github.com/Mimetis/aad_fastapi
Project-URL: Bug Tracker, https://github.com/Mimetis/aad_fastapi/issues
Project-URL: Documentation, https://mimetis.github.io/aad_fastapi
Author-email: Sébastien Pertus <sebastien.pertus@gmail.com>
Keywords: python
Classifier: License :: OSI Approved :: MIT License
Classifier: Operating System :: OS Independent
Classifier: Programming Language :: Python :: 3
Requires-Python: >=3.7
Requires-Dist: aiohttp==3.7.4.post0
Requires-Dist: async-asgi-testclient==1.4.6
Requires-Dist: authlib==0.15.4
Requires-Dist: azure-identity==1.6.0
Requires-Dist: azure-keyvault-certificates==4.2.1
Requires-Dist: azure-keyvault==4.1.0
Requires-Dist: fastapi==0.68.1
Requires-Dist: msal==1.12.0
